emantis-1.2.2.dist-info/METADATA
emantis-1.2.2.dist-info/WHEEL
emantis-1.2.2.dist-info/entry_points.txt
emantis-1.2.2.dist-info/licenses/COPYING
emantis/__init__.py
emantis/_cli.py
emantis/_gp_emulation.py
emantis/_read_data.py
emantis/_transformers.py
emantis/_types.py
emantis/_utils.py
emantis/_utils_inputs.py
emantis/data/cosmo_params_fR_emu_v1.txt
emantis/data/cosmo_params_fR_emu_v1_config.toml
emantis/data/cosmo_params_fR_emu_v2.txt
emantis/data/cosmo_params_fR_emu_v2_config.toml
emantis/data/cosmo_params_wCDM_emu_v2.txt
emantis/data/cosmo_params_wCDM_emu_v2_config.toml
emantis/data/fofr_matter_power_boost/cosmo_params.txt
emantis/data/fofr_matter_power_boost/kbins.h5
emantis/data/fofr_matter_power_boost/power_boosts_train.h5
emantis/data/halo_mass_function/halo_mass_function_fR_emu_v2_data.h5
emantis/data/halo_mass_function/halo_mass_function_fR_emu_v2_emulation_config.toml
emantis/data/halo_mass_function/halo_mass_function_wCDM_emu_v2_data.h5
emantis/data/halo_mass_function/halo_mass_function_wCDM_emu_v2_emulation_config.toml
emantis/data/matter_power_spectrum_nl_boost/matter_power_spectrum_nl_boost_wCDM_emu_v2_data.h5
emantis/data/matter_power_spectrum_nl_boost/matter_power_spectrum_nl_boost_wCDM_emu_v2_emulation_config.toml
emantis/data/matter_power_spectrum_nl_mg_boost/matter_power_spectrum_nl_mg_boost_fR_emu_v1_data.h5
emantis/data/matter_power_spectrum_nl_mg_boost/matter_power_spectrum_nl_mg_boost_fR_emu_v1_emulation_config.toml
emantis/data/matter_power_spectrum_nl_mg_boost/matter_power_spectrum_nl_mg_boost_fR_emu_v2_data.h5
emantis/data/matter_power_spectrum_nl_mg_boost/matter_power_spectrum_nl_mg_boost_fR_emu_v2_emulation_config.toml
emantis/data/sigma8/cosmo_params_LCDM.txt
emantis/data/sigma8/cosmo_params_LCDM_config.toml
emantis/data/sigma8/cosmo_params_wCDM.txt
emantis/data/sigma8/cosmo_params_wCDM_config.toml
emantis/data/sigma8/sigma8_LCDM_data.txt
emantis/data/sigma8/sigma8_LCDM_emulation_config.toml
emantis/data/sigma8/sigma8_wCDM_data.txt
emantis/data/sigma8/sigma8_wCDM_emulation_config.toml
emantis/exceptions.py
emantis/halo_mass_function.py
emantis/matter_power_spectrum.py
emantis-1.2.2.dist-info/RECORD
