Metadata-Version: 2.1
Name: emantis
Version: 1.2.2
Summary: A cosmological emulator for nonlinear large-scale structure formation studies in alternative dark energy and gravity theories.
Keywords: cosmology,emulator,large-scale structure,dark energy,modified gravity
Author-Email: =?utf-8?q?I=C3=B1igo_S=C3=A1ez_Casares?= <inigo.saez-casares@obspm.fr>
License: GPL-3.0-or-later
Classifier: Programming Language :: Python :: 3
Classifier: License :: OSI Approved :: GNU General Public License v3 (GPLv3)
Classifier: Operating System :: OS Independent
Classifier: Intended Audience :: Science/Research
Classifier: Topic :: Scientific/Engineering :: Physics
Project-URL: repository, https://gitlab.obspm.fr/e-mantis/e-mantis.git
Project-URL: documentation, https://e-mantis.pages.obspm.fr/e-mantis/index.html
Requires-Python: <3.15,>=3.10
Requires-Dist: h5py<4.0,>=3.8
Requires-Dist: scikit-learn<2,>=1
Requires-Dist: numpy<3.0,>=1.24
Requires-Dist: pydantic<3.0,>=2.6
Requires-Dist: tomli<3,>=2; python_version < "3.11"
Requires-Dist: joblib<2.0.0,>=1.3.2
